[ 
    { 
        "name"  : "Tuhin",
        "email"  : "tuhin@gmail.com",
        "age"  : 29,
        "city"  : 1
    },
    { 
        "name"  : "Shaki",
        "email"  : "shakib@gmail.com",
        "age"  : 32,
        "city"  : 2
    },
    { 
        "name"  : "Tasrif",
        "email"  : "tasrif@gmail.com",
        "age"  : 27,
        "city"  :3
    },
    { 
        "name"  : "Meem",
        "email"  : "meem@gmail.com",
        "age"  : 24,
        "city"  :4
    },
    { 
        "name"  : "Fima",
        "email"  : "fima@gmail.com",
        "age"  : 29,
        "city"  :5
    },
    { 
        "name"  : "Shakil",
        "email"  : "shakil@gmail.com",
        "age"  : 23,
        "city"  :6
    },
    { 
        "name"  : "Munna",
        "email"  : "munna@gmail.com",
        "age"  : 22,
        "city"  :7
    },
    { 
        "name"  : "Arfan",
        "email"  : "arfan@gmail.com",
        "age"  : 32,
        "city"  :8
    },
    { 
        "name"  : "Taniya",
        "email"  : "taniya@gmail.com",
        "age"  : 21,
        "city"  :9
    },
    { 
        "name"  : "Yasin",
        "email"  : "yasin@gmail.com",
        "age"  : 33,
        "city"  :10
    }

]